odoo/addons/sinli/CHANGELOG.md
odoo/addons/sinli/__init__.py
odoo/addons/sinli/__manifest__.py
odoo/addons/sinli/i18n/ca.po
odoo/addons/sinli/i18n/es.po
odoo/addons/sinli/models/__init__.py
odoo/addons/sinli/models/get_file.py
odoo/addons/sinli/models/res_company_sinli.py
odoo/addons/sinli/models/res_config_settings_sinli.py
odoo/addons/sinli/models/res_partner_sinli.py
odoo/addons/sinli/models/sinli_message.py
odoo/addons/sinli/models/sinli_mixin.py
odoo/addons/sinli/models/sinli_product_template.py
odoo/addons/sinli/models/sinli_purchase_order.py
odoo/addons/sinli/security/ir.model.access.csv
odoo/addons/sinli/static/description/icon.png
odoo/addons/sinli/static/src/sinli_import_menu.xml
odoo/addons/sinli/static/src/js/sinli_import_purchase_order_menu.js
odoo/addons/sinli/static/src/js/sinli_import_sale_order_menu.js
odoo/addons/sinli/views/download_file.xml
odoo/addons/sinli/views/export_libro_view.xml
odoo/addons/sinli/views/export_purchase_order_view.xml
odoo/addons/sinli/views/res_config_settings_sinli_view.xml
odoo/addons/sinli/views/res_partner_sinli_view.xml
odoo/addons/sinli/views/sinli_dialog_view.xml
odoo/addons/sinli/views/sinli_message_view.xml
odoo/addons/sinli/wizards/__init__.py
odoo/addons/sinli/wizards/export_sinli/__init__.py
odoo/addons/sinli/wizards/export_sinli/export_sinli.py
odoo/addons/sinli/wizards/export_sinli/export_sinli.xml
odoo/addons/sinli/wizards/import_sinli/__init__.py
odoo/addons/sinli/wizards/import_sinli/import_purchase_order_sinli.xml
odoo/addons/sinli/wizards/import_sinli/import_sale_order_sinli.xml
odoo/addons/sinli/wizards/import_sinli/import_sinli.py
odoo_addon_sinli-17.0.1.2.0.2.dist-info/METADATA
odoo_addon_sinli-17.0.1.2.0.2.dist-info/WHEEL
odoo_addon_sinli-17.0.1.2.0.2.dist-info/top_level.txt
odoo_addon_sinli-17.0.1.2.0.2.dist-info/RECORD
