Metadata-Version: 2.1
Name: odoo-addon-sinli
Version: 17.0.1.2.0.2
Requires-Python: >=3.10
Requires-Dist: odoo-addon-gestion_editorial>=17.0dev,<17.1dev
Requires-Dist: odoo>=17.0a,<17.1dev
Requires-Dist: python-stdnum==1.20
Requires-Dist: sinli==1.3.0
Summary: =?utf-8?q?M=C3=B3dulo_para_la_integraci=C3=B3n_de_sinli_en_Odoo=2E?=
Home-page: https://framagit.org/devcontrol
License: OPL-1
Author: Colectivo DEVCONTROL
Classifier: Programming Language :: Python
Classifier: Framework :: Odoo
Classifier: Framework :: Odoo :: 17.0
